artemis/__init__.py
artemis/artemis.py
artemis/events.py
artemis/parameter.py
artemis/patient.py
artemis/plotting.py
artemis/thresholds.py
artemis/virtuals.py
hpi_ch_artemis-0.1.dist-info/LICENSE
hpi_ch_artemis-0.1.dist-info/METADATA
hpi_ch_artemis-0.1.dist-info/WHEEL
hpi_ch_artemis-0.1.dist-info/top_level.txt
hpi_ch_artemis-0.1.dist-info/RECORD
