Metadata-Version: 2.1
Name: hpi-ch-artemis
Version: 0.1
Summary: ARTEMIS: An Alarm Threshold Mining System
Home-page: https://github.com/HPI-CH/artemis
Author: Jonas Chromik
Author-email: jonas.chromik@hpi.de
License: UNKNOWN
Platform: UNKNOWN
Classifier: Programming Language :: Python :: 3
Classifier: License :: OSI Approved :: MIT License
Classifier: Operating System :: OS Independent
Requires-Python: >=3.6
License-File: LICENSE
